runstardist/__init__.py
runstardist/__version__.py
runstardist/augment.py
runstardist/config.py
runstardist/evaluate.py
runstardist/predict.py
runstardist/train.py
runstardist/utils.py
runstardist/dataio/__init__.py
runstardist/dataio/hdf5.py
runstardist/dataio/tiff.py
tests/__init__.py
tests/test_integration.py
run_stardist-0.0.5.dist-info/METADATA
run_stardist-0.0.5.dist-info/WHEEL
run_stardist-0.0.5.dist-info/entry_points.txt
run_stardist-0.0.5.dist-info/top_level.txt
run_stardist-0.0.5.dist-info/RECORD
