Metadata-Version: 2.4
Name: run-stardist
Version: 0.0.5
Summary: Train and use StarDist models
Home-page: https://github.com/kreshuklab/go-nuclear
Author: Qin Yu
Author-email: qin.yu@embl.de
License: MIT
Project-URL: Documentation, https://kreshuklab.github.io/go-nuclear/
Project-URL: Source, https://github.com/kreshuklab/go-nuclear
Project-URL: Bug Tracker, https://github.com/kreshuklab/go-nuclear/issues
Dynamic: author
Dynamic: author-email
Dynamic: home-page
Dynamic: license
Dynamic: project-url
Dynamic: summary
